pycasx/__init__.py
pycasx/py.typed
pycasx/acas/__init__.py
pycasx/acas/acasx.py
pycasx/acas/hcas.py
pycasx/acas/runner.py
pycasx/acas/vcas.py
pycasx/assets/neural_networks/hcas/HCAS_rect_v6_pra0_tau00_25HU_3000.nnet
pycasx/assets/neural_networks/hcas/HCAS_rect_v6_pra0_tau05_25HU_3000.nnet
pycasx/assets/neural_networks/hcas/HCAS_rect_v6_pra0_tau10_25HU_3000.nnet
pycasx/assets/neural_networks/hcas/HCAS_rect_v6_pra0_tau15_25HU_3000.nnet
pycasx/assets/neural_networks/hcas/HCAS_rect_v6_pra0_tau20_25HU_3000.nnet
pycasx/assets/neural_networks/hcas/HCAS_rect_v6_pra0_tau30_25HU_3000.nnet
pycasx/assets/neural_networks/hcas/HCAS_rect_v6_pra0_tau40_25HU_3000.nnet
pycasx/assets/neural_networks/hcas/HCAS_rect_v6_pra0_tau60_25HU_3000.nnet
pycasx/assets/neural_networks/hcas/HCAS_rect_v6_pra1_tau00_25HU_3000.nnet
pycasx/assets/neural_networks/hcas/HCAS_rect_v6_pra1_tau05_25HU_3000.nnet
pycasx/assets/neural_networks/hcas/HCAS_rect_v6_pra1_tau10_25HU_3000.nnet
pycasx/assets/neural_networks/hcas/HCAS_rect_v6_pra1_tau15_25HU_3000.nnet
pycasx/assets/neural_networks/hcas/HCAS_rect_v6_pra1_tau20_25HU_3000.nnet
pycasx/assets/neural_networks/hcas/HCAS_rect_v6_pra1_tau30_25HU_3000.nnet
pycasx/assets/neural_networks/hcas/HCAS_rect_v6_pra1_tau40_25HU_3000.nnet
pycasx/assets/neural_networks/hcas/HCAS_rect_v6_pra1_tau60_25HU_3000.nnet
pycasx/assets/neural_networks/hcas/HCAS_rect_v6_pra2_tau00_25HU_3000.nnet
pycasx/assets/neural_networks/hcas/HCAS_rect_v6_pra2_tau05_25HU_3000.nnet
pycasx/assets/neural_networks/hcas/HCAS_rect_v6_pra2_tau10_25HU_3000.nnet
pycasx/assets/neural_networks/hcas/HCAS_rect_v6_pra2_tau15_25HU_3000.nnet
pycasx/assets/neural_networks/hcas/HCAS_rect_v6_pra2_tau20_25HU_3000.nnet
pycasx/assets/neural_networks/hcas/HCAS_rect_v6_pra2_tau30_25HU_3000.nnet
pycasx/assets/neural_networks/hcas/HCAS_rect_v6_pra2_tau40_25HU_3000.nnet
pycasx/assets/neural_networks/hcas/HCAS_rect_v6_pra2_tau60_25HU_3000.nnet
pycasx/assets/neural_networks/hcas/HCAS_rect_v6_pra3_tau00_25HU_3000.nnet
pycasx-1.0.0.dist-info/CC-BY-4.0.txt
pycasx-1.0.0.dist-info/METADATA
pycasx-1.0.0.dist-info/MIT.txt
pycasx-1.0.0.dist-info/WHEEL
pycasx-1.0.0.dist-info/entry_points.txt
pycasx-1.0.0.dist-info/top_level.txt
pycasx-1.0.0.dist-info/RECORD
