Metadata-Version: 2.1
Name: pycasx
Version: 1.0.0
Summary: A Python implementation of ACAS XA and ACAS XU for Flightgear.
Author-email: Johann Christensen <johann.christensen@dlr.de>
License: MIT License
Project-URL: Documentation, https://pycasx.readthedocs.io/
Project-URL: Homepage, https://github.com/DLR-KI/pycasx.git
Project-URL: Source, https://github.com/DLR-KI/pycasx.git
Project-URL: Tracker, https://github.com/DLR-KI/pycasx/-/issues
Platform: macosx_13_x86_64
Platform: manylinux2014_x86_64
Platform: win_amd64
Classifier: Development Status :: 4 - Beta
Classifier: Environment :: X11 Applications
Classifier: Intended Audience :: Developers
Classifier: Intended Audience :: End Users/Desktop
Classifier: Intended Audience :: Science/Research
Classifier: License :: OSI Approved :: MIT License
Classifier: Natural Language :: English
Classifier: Operating System :: MacOS :: MacOS X
Classifier: Operating System :: Microsoft :: Windows :: Windows 10
Classifier: Operating System :: Microsoft :: Windows :: Windows 11
Classifier: Operating System :: POSIX :: Linux
Classifier: Programming Language :: Python :: 3 :: Only
Classifier: Programming Language :: Python :: 3.8
Classifier: Programming Language :: Python :: 3.9
Classifier: Programming Language :: Python :: 3.10
Classifier: Programming Language :: Python :: 3.11
Classifier: Programming Language :: Python :: Implementation :: CPython
Classifier: Topic :: Games/Entertainment :: Simulation
Classifier: Topic :: Scientific/Engineering :: Artificial Intelligence
Classifier: Typing :: Typed
Requires-Python: <3.12,>=3.8
License-File: LICENSES/CC-BY-4.0.txt
License-File: LICENSES/MIT.txt
Requires-Dist: flightgear-python==1.6.0
Requires-Dist: fastapi[all]==0.105.0
Requires-Dist: hydra-core==1.3.2
Requires-Dist: loguru==0.7.2
Requires-Dist: lxml==5.1.0
Requires-Dist: numpy==1.24.4
Requires-Dist: onnx==1.14.1
Requires-Dist: onnx2torch==1.5.12
Requires-Dist: onnxruntime==1.16.1
Requires-Dist: pillow==10.1.0
Requires-Dist: pint==0.21.1
Requires-Dist: pyproj==3.5.0
Requires-Dist: libtmux==0.31.0.post0
Requires-Dist: scipy==1.10.1
Requires-Dist: torch==2.1.0
Requires-Dist: tqdm==4.66.2
Requires-Dist: rich==13.7.1
Provides-Extra: all
Requires-Dist: pycasx[dev,docs,tests]; extra == "all"
Provides-Extra: dev
Requires-Dist: lxml-stubs; extra == "dev"
Requires-Dist: pre-commit>=3.5.0; extra == "dev"
Requires-Dist: reuse>=4.0.0; extra == "dev"
Provides-Extra: docs
Requires-Dist: sphinx==7.1.2; extra == "docs"
Requires-Dist: sphinx-autodoc-typehints==1.25.2; extra == "docs"
Requires-Dist: sphinx-rtd-theme==2.0.0; extra == "docs"
Requires-Dist: sphinx-autoapi==3.0.0; extra == "docs"
Provides-Extra: full
Requires-Dist: pycasx[all]; extra == "full"
Provides-Extra: tests
Requires-Dist: coverage; extra == "tests"
Requires-Dist: flake8-bugbear; extra == "tests"
Requires-Dist: flake8-builtins; extra == "tests"
Requires-Dist: flake8-comprehensions; extra == "tests"
Requires-Dist: flake8-docstrings-complete; extra == "tests"
Requires-Dist: flake8-docstrings; extra == "tests"
Requires-Dist: flake8-pyproject; extra == "tests"
Requires-Dist: flake8-simplify; extra == "tests"
Requires-Dist: flake8; extra == "tests"
Requires-Dist: mypy; extra == "tests"
Requires-Dist: parameterized; extra == "tests"
Requires-Dist: pep8-naming; extra == "tests"
Requires-Dist: pycodestyle; extra == "tests"
Requires-Dist: pydoclint; extra == "tests"
Requires-Dist: pylint-per-file-ignores; extra == "tests"
Requires-Dist: pylint; extra == "tests"
Requires-Dist: pytest-cov; extra == "tests"
Requires-Dist: pytest>=7.4.0; extra == "tests"
Requires-Dist: shapely; extra == "tests"
Requires-Dist: types-requests; extra == "tests"
